agiocli/__init__.py
agiocli/__main__.py
agiocli/api_client.py
agiocli/utils.py
agiocli-0.5.1.dist-info/LICENSE
agiocli-0.5.1.dist-info/METADATA
agiocli-0.5.1.dist-info/WHEEL
agiocli-0.5.1.dist-info/entry_points.txt
agiocli-0.5.1.dist-info/top_level.txt
agiocli-0.5.1.dist-info/RECORD
