Metadata-Version: 2.1
Name: agiocli
Version: 0.5.1
Summary: A command line interface to autograder.io
Home-page: https://github.com/eecs485staff/agio-cli/
Author: Andrew DeOrio
Author-email: awdeorio@umich.edu
License: MIT
Keywords: autograder,autograder.io,auto grader,agcli,agio,ag-cli,agio-cli
Requires-Python: >=3.7
License-File: LICENSE
Requires-Dist: click
Requires-Dist: pick (>=2.0.0)
Requires-Dist: python-dateutil
Requires-Dist: requests
Provides-Extra: dev
Requires-Dist: pdbpp ; extra == 'dev'
Requires-Dist: twine ; extra == 'dev'
Requires-Dist: tox ; extra == 'dev'
Provides-Extra: test
Requires-Dist: check-manifest ; extra == 'test'
Requires-Dist: freezegun ; extra == 'test'
Requires-Dist: pycodestyle ; extra == 'test'
Requires-Dist: pydocstyle ; extra == 'test'
Requires-Dist: pylint ; extra == 'test'
Requires-Dist: pytest ; extra == 'test'
Requires-Dist: pytest-cov ; extra == 'test'
Requires-Dist: pytest-mock ; extra == 'test'
Requires-Dist: requests-mock ; extra == 'test'
